{
  "recentFiles": [
    {
      "basename": "2023-03-27-Mon",
      "path": "Diary/2023-03-27-Mon.md"
    },
    {
      "basename": "2023-03-26-Sun",
      "path": "Diary/2023-03-26-Sun.md"
    },
    {
      "basename": "2023-03-25-Sat",
      "path": "Diary/2023-03-25-Sat.md"
    },
    {
      "basename": "2023-03-24-Fri",
      "path": "Diary/2023-03-24-Fri.md"
    },
    {
      "basename": "2023-03-23-Thu",
      "path": "Diary/2023-03-23-Thu.md"
    },
    {
      "basename": "2023-03-22-Wed",
      "path": "Diary/2023-03-22-Wed.md"
    },
    {
      "basename": "2023-03-21-Tue",
      "path": "Diary/2023-03-21-Tue.md"
    },
    {
      "basename": "2023-03-20-Mon",
      "path": "Diary/2023-03-20-Mon.md"
    },
    {
      "basename": "2023-03-19-Sun",
      "path": "Diary/2023-03-19-Sun.md"
    },
    {
      "basename": "2023-03-18-Sat",
      "path": "Diary/2023-03-18-Sat.md"
    },
    {
      "basename": "2023-03-17-Fri",
      "path": "Diary/2023-03-17-Fri.md"
    },
    {
      "basename": "MarkdownTemplate",
      "path": "MarkdownTemplate.md"
    },
    {
      "basename": "2023-03-16-Thu",
      "path": "Diary/2023-03-16-Thu.md"
    },
    {
      "basename": "Lora SX1276",
      "path": "Lora模块开发/Lora SX1276.md"
    },
    {
      "basename": "[",
      "path": "[.md"
    },
    {
      "basename": "2023-06-07-Wed",
      "path": "Diary/2023-06-07-Wed.md"
    },
    {
      "basename": "2023-06-12-Mon",
      "path": "Diary/2023-06-12-Mon.md"
    },
    {
      "basename": "2023-06-09-Fri",
      "path": "Diary/2023-06-09-Fri.md"
    },
    {
      "basename": "2023-06-06-Tue",
      "path": "Diary/2023-06-06-Tue.md"
    },
    {
      "basename": "2023-06-05-Mon",
      "path": "Diary/2023-06-05-Mon.md"
    },
    {
      "basename": "stm32烧录",
      "path": "sym32/stm32烧录.md"
    },
    {
      "basename": "Cotex-M内核基础介绍",
      "path": "sym32/Cotex-M内核基础介绍.md"
    },
    {
      "basename": "ARM Cortex-M",
      "path": "ARM/ARM Cortex-M.md"
    },
    {
      "basename": "LIN",
      "path": "CAN/LIN.md"
    },
    {
      "basename": "CAN",
      "path": "CAN/CAN.md"
    },
    {
      "basename": "MAC",
      "path": "网络通信/MAC.md"
    },
    {
      "basename": "示波器参数",
      "path": "示波器参数/示波器参数.md"
    },
    {
      "basename": "2023-06-01-Thu",
      "path": "Diary/2023-06-01-Thu.md"
    },
    {
      "basename": "Lora 简介",
      "path": "Lora模块开发/Lora 简介.md"
    },
    {
      "basename": "Lora 脉宽调制技术",
      "path": "Lora模块开发/Lora 脉宽调制技术.md"
    },
    {
      "basename": "SX1278驱动",
      "path": "Lora模块开发/SX1278驱动.md"
    },
    {
      "basename": "2023-05-31-Wed",
      "path": "Diary/2023-05-31-Wed.md"
    },
    {
      "basename": "2023-05-30-Tue",
      "path": "Diary/2023-05-30-Tue.md"
    },
    {
      "basename": "2023-05-25-Thu",
      "path": "Diary/2023-05-25-Thu.md"
    },
    {
      "basename": "2023-05-18-Thu",
      "path": "Diary/2023-05-18-Thu.md"
    },
    {
      "basename": "2023-05-20-Sat",
      "path": "Diary/2023-05-20-Sat.md"
    },
    {
      "basename": "2023-05-22-Mon",
      "path": "Diary/2023-05-22-Mon.md"
    },
    {
      "basename": "2023-05-24-Wed",
      "path": "Diary/2023-05-24-Wed.md"
    },
    {
      "basename": "2023-05-23-Tue",
      "path": "Diary/2023-05-23-Tue.md"
    },
    {
      "basename": "2023-05-17-Wed",
      "path": "Diary/2023-05-17-Wed.md"
    },
    {
      "basename": "2023-05-15-Mon",
      "path": "Diary/2023-05-15-Mon.md"
    },
    {
      "basename": "2023-05-13-Sat",
      "path": "Diary/2023-05-13-Sat.md"
    },
    {
      "basename": "2023-04-25-Tue",
      "path": "Diary/2023-04-25-Tue.md"
    },
    {
      "basename": "2023-04-24-Mon",
      "path": "Diary/2023-04-24-Mon.md"
    },
    {
      "basename": "2023-04-23-Sun",
      "path": "Diary/2023-04-23-Sun.md"
    },
    {
      "basename": "2023-04-22-Sat",
      "path": "Diary/2023-04-22-Sat.md"
    },
    {
      "basename": "2023-04-20-Thu",
      "path": "Diary/2023-04-20-Thu.md"
    },
    {
      "basename": "2023-04-19-Wed",
      "path": "Diary/2023-04-19-Wed.md"
    },
    {
      "basename": "2023-04-18-Tue",
      "path": "Diary/2023-04-18-Tue.md"
    },
    {
      "basename": "2023-04-17-Mon",
      "path": "Diary/2023-04-17-Mon.md"
    }
  ],
  "omittedPaths": [],
  "maxLength": null,
  "openType": "tab"
}